rtrimmer/__init__.py
rtrimmer/__main__.py
rtrimmer/cli.py
rtrimmer/core.py
rtrimmer/version.py
rtrimmer-0.1.0.dist-info/licenses/LICENSE
rtrimmer-0.1.0.dist-info/METADATA
rtrimmer-0.1.0.dist-info/WHEEL
rtrimmer-0.1.0.dist-info/entry_points.txt
rtrimmer-0.1.0.dist-info/top_level.txt
rtrimmer-0.1.0.dist-info/RECORD
