Metadata-Version: 2.4
Name: rtrimmer
Version: 0.1.0
Summary: Lightweight Python package to trim RTTM diarization files and audio files
Home-page: https://github.com/eddiegulay/rtrimmer
Author: eddiegulay
Author-email: edgargulay@outlook.com.com
Keywords: rttm,diarization,audio,trimming,pyannote
Classifier: Programming Language :: Python :: 3
Classifier: Programming Language :: Python :: 3.8
Classifier: Programming Language :: Python :: 3.9
Classifier: Programming Language :: Python :: 3.10
Classifier: Programming Language :: Python :: 3.11
Classifier: License :: OSI Approved :: MIT License
Classifier: Operating System :: OS Independent
Classifier: Topic :: Multimedia :: Sound/Audio
Classifier: Topic :: Scientific/Engineering :: Information Analysis
Requires-Python: >=3.8
License-File: LICENSE
Requires-Dist: ffmpeg-python>=0.2.0
Requires-Dist: pyannote.core>=4.5.1
Dynamic: author
Dynamic: author-email
Dynamic: classifier
Dynamic: description
Dynamic: description-content-type
Dynamic: home-page
Dynamic: keywords
Dynamic: license-file
Dynamic: requires-dist
Dynamic: requires-python
Dynamic: summary
